Metadata-Version: 2.1
Name: races-reports-generator
Version: 1.0.0
Summary: Just races reports generator
Home-page: UNKNOWN
Author: Drakosha295
License: UNKNOWN
Platform: UNKNOWN
License-File: LICENSE.txt
